cities/__init__.py
cities/admin.py
cities/conf.py
cities/managers.py
cities/models.py
cities/util.py
cities/management/__init__.py
cities/management/commands/__init__.py
cities/management/commands/cities.py
cities/migrations/0001_initial.py
cities/migrations/0002_continent_models_and_foreign_keys.py
cities/migrations/0003_add_verbose_name_and_related_names.py
cities/migrations/0004_rename_languages_to_language_codes.py
cities/migrations/0005_add_foreignkeys_to_postalcode.py
cities/migrations/0006_typify_alt_names_and_add_is_historic.py
cities/migrations/0007_add_currency_and_postal_code_fields_to_country_model.py
cities/migrations/0008_add_code_to_district.py
cities/migrations/0009_add_slug_fields_to_models.py
cities/migrations/0010_adjust_unique_attributes.py
cities/migrations/0011_auto_20180108_0706.py
cities/migrations/__init__.py
cities/plugin/__init__.py
cities/plugin/postal_code_ca.py
cities/plugin/reset_queries.py
cities/south_migrations/0001_initial.py
cities/south_migrations/__init__.py
django_cities-0.6.1.dist-info/LICENSE
django_cities-0.6.1.dist-info/METADATA
django_cities-0.6.1.dist-info/WHEEL
django_cities-0.6.1.dist-info/top_level.txt
django_cities-0.6.1.dist-info/RECORD
